automated_document_parser/__init__.py
automated_document_parser/config.py
automated_document_parser/core.py
automated_document_parser/main.py
automated_document_parser/utils.py
automated_document_parser/loaders/__init__.py
automated_document_parser/loaders/file_loaders.py
automated_document_parser/loaders/file_load/__init__.py
automated_document_parser/loaders/file_load/base.py
automated_document_parser/loaders/file_load/csv_loader.py
automated_document_parser/loaders/file_load/docx_loader.py
automated_document_parser/loaders/file_load/html_loader.py
automated_document_parser/loaders/file_load/json_loader.py
automated_document_parser/loaders/file_load/text_loader.py
automated_document_parser/loaders/pdf_load/__init__.py
automated_document_parser/loaders/pdf_load/base.py
automated_document_parser/loaders/pdf_load/loader.py
automated_document_parser/loaders/pdf_load/mathpix_loader.py
automated_document_parser/loaders/pdf_load/opendataloader_loader.py
automated_document_parser/loaders/pdf_load/pdfplumber_loader.py
automated_document_parser/loaders/pdf_load/pymupdf4llm_loader.py
automated_document_parser/loaders/pdf_load/pymupdf_loader.py
automated_document_parser/loaders/pdf_load/pypdf_loader.py
automated_document_parser/loaders/pdf_load/pypdfium2_loader.py
automated_document_parser/loaders/pdf_load/textract_loader.py
automated_document_parser/loaders/pdf_load/unstructured_loader.py
automated_document_parser-0.1.6.dist-info/METADATA
automated_document_parser-0.1.6.dist-info/WHEEL
automated_document_parser-0.1.6.dist-info/licenses/LICENSE
automated_document_parser-0.1.6.dist-info/RECORD
