Metadata-Version: 2.4
Name: automated-document-parser
Version: 0.1.6
Summary: A powerful and automated document parser built with LangChain for intelligent document processing
Project-URL: Homepage, https://github.com/Pulkit12dhingra/automated-document-parser
Project-URL: Documentation, https://pulkit12dhingra.github.io/automated-document-parser/
Project-URL: Repository, https://github.com/Pulkit12dhingra/automated-document-parser
Project-URL: Issues, https://github.com/Pulkit12dhingra/automated-document-parser/issues
Author-email: Pulkit Dhingra <pulkit12dhingra@example.com>
License: MIT License
License-File: LICENSE
Keywords: document-parser,langchain,nlp
Classifier: Development Status :: 3 - Alpha
Classifier: Intended Audience :: Developers
Classifier: License :: OSI Approved :: MIT License
Classifier: Programming Language :: Python :: 3
Classifier: Programming Language :: Python :: 3.13
Requires-Python: >=3.13
Requires-Dist: build>=1.3.0
Requires-Dist: faiss-cpu>=1.12.0
Requires-Dist: langchain-community>=0.3.0
Requires-Dist: langchain-huggingface>=1.0.1
Requires-Dist: langchain-text-splitters>=1.0.0
Requires-Dist: langchain>=0.3.0
Requires-Dist: pypdf>=5.1.0
Requires-Dist: python-docx>=1.1.0
Requires-Dist: python-magic>=0.4.27
Requires-Dist: sentence-transformers>=5.1.2
Requires-Dist: sphinx>=8.2.3
Requires-Dist: torch>=2.9.0
Requires-Dist: transformers>=4.57.1
Provides-Extra: dev
Requires-Dist: pre-commit>=4.0.1; extra == 'dev'
Requires-Dist: pytest-cov>=7.0.0; extra == 'dev'
Requires-Dist: pytest>=8.3.4; extra == 'dev'
Requires-Dist: ruff>=0.14.4; extra == 'dev'
Requires-Dist: twine>=6.2.0; extra == 'dev'
